authease/__init__.py
authease/auth_core/__init__.py
authease/auth_core/admin.py
authease/auth_core/apps.py
authease/auth_core/manager.py
authease/auth_core/models.py
authease/auth_core/serializers.py
authease/auth_core/urls.py
authease/auth_core/utils.py
authease/auth_core/migrations/0001_initial.py
authease/auth_core/migrations/0002_alter_user_options_alter_onetimepassword_code_and_more.py
authease/auth_core/migrations/0003_onetimepassword_created_at.py
authease/auth_core/migrations/__init__.py
authease/auth_core/tests/__init__.py
authease/auth_core/tests/test_login_views.py
authease/auth_core/tests/test_models.py
authease/auth_core/tests/test_registration_view.py
authease/auth_core/tests/test_serializers.py
authease/auth_core/tests/test_utils.py
authease/auth_core/tests/test_verification_passwordreset_views.py
authease/auth_core/views/__init__.py
authease/auth_core/views/authentication_views.py
authease/auth_core/views/password_views.py
authease/oauth/__init__.py
authease/oauth/admin.py
authease/oauth/apps.py
authease/oauth/github.py
authease/oauth/models.py
authease/oauth/serializers.py
authease/oauth/tests.py
authease/oauth/urls.py
authease/oauth/utils.py
authease/oauth/views.py
authease-2.0.0.dist-info/LICENSE
authease-2.0.0.dist-info/METADATA
authease-2.0.0.dist-info/WHEEL
authease-2.0.0.dist-info/top_level.txt
authease-2.0.0.dist-info/RECORD
